python_speech_features_cuda/__init__.py
python_speech_features_cuda/__init___.py
python_speech_features_cuda/_buf.py
python_speech_features_cuda/_env.py
python_speech_features_cuda/_misc.py
python_speech_features_cuda/main.py
python_speech_features_cuda/sigproc.py
python_speech_features_cuda-0.0.10.dist-info/LICENSE
python_speech_features_cuda-0.0.10.dist-info/METADATA
python_speech_features_cuda-0.0.10.dist-info/WHEEL
python_speech_features_cuda-0.0.10.dist-info/top_level.txt
python_speech_features_cuda-0.0.10.dist-info/RECORD
